test/__init__.py
test/fold_settings.py
test/test_fold.py
test/test_unfold.py
test/test_unfold_transpose.py
test/test_utils.py
test/unfold_settings.py
test/unfold_transpose_settings.py
test/utils.py
test/utils_settings.py
unfoldNd/__init__.py
unfoldNd/fold.py
unfoldNd/unfold.py
unfoldNd/unfold_transpose.py
unfoldNd/utils.py
unfoldNd-0.2.2.dist-info/LICENSE
unfoldNd-0.2.2.dist-info/METADATA
unfoldNd-0.2.2.dist-info/WHEEL
unfoldNd-0.2.2.dist-info/top_level.txt
unfoldNd-0.2.2.dist-info/RECORD
